zip_folder_sync-0.1.dist-info/DESCRIPTION.rst
zip_folder_sync-0.1.dist-info/METADATA
zip_folder_sync-0.1.dist-info/RECORD
zip_folder_sync-0.1.dist-info/WHEEL
zip_folder_sync-0.1.dist-info/entry_points.txt
zip_folder_sync-0.1.dist-info/metadata.json
zip_folder_sync-0.1.dist-info/top_level.txt
zip_sync/__init__.py
zip_sync/__main__.py
