Metadata-Version: 2.0
Name: zip-folder-sync
Version: 0.1
Summary: Synchronize a zip file with a folder.
Home-page: UNKNOWN
Author: Mars Galactic
Author-email: UNKNOWN
License: UNKNOWN
Platform: UNKNOWN
